rbfmvar/__init__.py
rbfmvar/dimension_flow_visual.py
rbfmvar/hypothesis_tests.py
rbfmvar/kernel_estimators.py
rbfmvar/rbfm_var_diagnostic.py
rbfmvar/rbfmvar_estimator.py
rbfmvar/utils.py
rbfmvar-1.0.2.dist-info/licenses/LICENSE
rbfmvar-1.0.2.dist-info/METADATA
rbfmvar-1.0.2.dist-info/WHEEL
rbfmvar-1.0.2.dist-info/top_level.txt
rbfmvar-1.0.2.dist-info/RECORD
