Metadata-Version: 2.4
Name: rbfmvar
Version: 1.0.2
Summary: Residual-Based Fully Modified Vector Autoregression for mixtures of I(0), I(1), and I(2) processes
Home-page: https://github.com/merwanroudane/RBFMVAR
Author: Dr. Merwan Roudane
Author-email: "Dr. Merwan Roudane" <merwanroudane920@gmail.com>
Maintainer-email: "Dr. Merwan Roudane" <merwanroudane920@gmail.com>
License: MIT
Project-URL: Homepage, https://github.com/merwanroudane/RBFMVAR
Project-URL: Documentation, https://github.com/merwanroudane/RBFMVAR#readme
Project-URL: Repository, https://github.com/merwanroudane/RBFMVAR
Project-URL: Bug Reports, https://github.com/merwanroudane/RBFMVAR/issues
Project-URL: Changelog, https://github.com/merwanroudane/RBFMVAR/blob/main/CHANGELOG.md
Keywords: econometrics,VAR,vector-autoregression,cointegration,I(2),time-series,nonstationary,unit-root,RBFM-VAR,Granger-causality
Classifier: Development Status :: 4 - Beta
Classifier: Intended Audience :: Science/Research
Classifier: Intended Audience :: Financial and Insurance Industry
Classifier: Topic :: Scientific/Engineering :: Mathematics
Classifier: Topic :: Scientific/Engineering :: Information Analysis
Classifier: Topic :: Office/Business :: Financial
Classifier: License :: OSI Approved :: MIT License
Classifier: Programming Language :: Python :: 3
Classifier: Programming Language :: Python :: 3.7
Classifier: Programming Language :: Python :: 3.8
Classifier: Programming Language :: Python :: 3.9
Classifier: Programming Language :: Python :: 3.10
Classifier: Programming Language :: Python :: 3.11
Classifier: Programming Language :: Python :: 3.12
Classifier: Operating System :: OS Independent
Requires-Python: >=3.7
License-File: LICENSE
Requires-Dist: numpy>=1.20.0
Requires-Dist: scipy>=1.7.0
Requires-Dist: pandas>=1.3.0
Requires-Dist: matplotlib>=3.3.0
Provides-Extra: dev
Requires-Dist: pytest>=6.0; extra == "dev"
Requires-Dist: pytest-cov>=2.0; extra == "dev"
Requires-Dist: black>=21.0; extra == "dev"
Requires-Dist: flake8>=3.9; extra == "dev"
Requires-Dist: mypy>=0.910; extra == "dev"
Requires-Dist: isort>=5.0; extra == "dev"
Provides-Extra: docs
Requires-Dist: sphinx>=4.0; extra == "docs"
Requires-Dist: sphinx-rtd-theme>=0.5; extra == "docs"
Requires-Dist: numpydoc>=1.1; extra == "docs"
Provides-Extra: all
Requires-Dist: rbfmvar[dev,docs]; extra == "all"
Dynamic: author
Dynamic: home-page
Dynamic: license-file
Dynamic: requires-python
